workato_platform_cli/__init__.py
workato_platform_cli/_version.py
workato_platform_cli/cli/__init__.py
workato_platform_cli/cli/containers.py
workato_platform_cli/cli/commands/__init__.py
workato_platform_cli/cli/commands/api_clients.py
workato_platform_cli/cli/commands/api_collections.py
workato_platform_cli/cli/commands/assets.py
workato_platform_cli/cli/commands/connections.py
workato_platform_cli/cli/commands/data_tables.py
workato_platform_cli/cli/commands/guide.py
workato_platform_cli/cli/commands/init.py
workato_platform_cli/cli/commands/profiles.py
workato_platform_cli/cli/commands/properties.py
workato_platform_cli/cli/commands/pull.py
workato_platform_cli/cli/commands/workspace.py
workato_platform_cli/cli/commands/connectors/__init__.py
workato_platform_cli/cli/commands/connectors/command.py
workato_platform_cli/cli/commands/connectors/connector_manager.py
workato_platform_cli/cli/commands/projects/__init__.py
workato_platform_cli/cli/commands/projects/command.py
workato_platform_cli/cli/commands/projects/project_manager.py
workato_platform_cli/cli/commands/push/__init__.py
workato_platform_cli/cli/commands/push/command.py
workato_platform_cli/cli/commands/recipes/__init__.py
workato_platform_cli/cli/commands/recipes/command.py
workato_platform_cli/cli/commands/recipes/validator.py
workato_platform_cli/cli/resources/data/connection-data.json
workato_platform_cli/cli/resources/data/picklist-data.json
workato_platform_cli/cli/resources/docs/README.md
workato_platform_cli/cli/resources/docs/actions.md
workato_platform_cli/cli/resources/docs/block-structure.md
workato_platform_cli/cli/resources/docs/connections-parameters.md
workato_platform_cli/cli/resources/docs/data-mapping.md
workato_platform_cli/cli/resources/docs/formulas.md
workato_platform_cli/cli/resources/docs/naming-conventions.md
workato_platform_cli/cli/resources/docs/recipe-deployment-workflow.md
workato_platform_cli/cli/resources/docs/recipe-fundamentals.md
workato_platform_cli-1.0.3.dist-info/METADATA
workato_platform_cli-1.0.3.dist-info/WHEEL
workato_platform_cli-1.0.3.dist-info/entry_points.txt
workato_platform_cli-1.0.3.dist-info/licenses/LICENSE
workato_platform_cli-1.0.3.dist-info/RECORD
