Metadata-Version: 2.4
Name: workato-platform-cli
Version: 1.0.3
Summary: CLI tool for the Workato Platform
Project-URL: Homepage, https://github.com/workato-devs/workato-platform-cli
Project-URL: Repository, https://github.com/workato-devs/workato-platform-cli.git
Project-URL: Issues, https://github.com/workato-devs/workato-platform-cli/issues
Author-email: Workato CLI Team <workato-devs@workato.com>
License: MIT
License-File: LICENSE
Keywords: api,automation,cli,workato
Classifier: Development Status :: 4 - Beta
Classifier: Environment :: Console
Classifier: Intended Audience :: Developers
Classifier: License :: OSI Approved :: MIT License
Classifier: Operating System :: OS Independent
Classifier: Programming Language :: Python :: 3
Classifier: Programming Language :: Python :: 3.11
Classifier: Programming Language :: Python :: 3.12
Classifier: Programming Language :: Python :: 3.13
Classifier: Topic :: Software Development :: Libraries :: Python Modules
Requires-Python: >=3.11
Requires-Dist: aiohttp-retry>=2.8.0
Requires-Dist: aiohttp>=3.8.0
Requires-Dist: asyncclick>=8.3.0
Requires-Dist: cbor2>=5.7.0
Requires-Dist: certifi>=2025.8.3
Requires-Dist: dependency-injector>=4.41.0
Requires-Dist: inquirer>=3.1.0
Requires-Dist: keyring>=25.6.0
Requires-Dist: packaging>=21.0
Requires-Dist: prompt-toolkit>=3.0.0
Requires-Dist: pydantic-settings>=2.11.0
Requires-Dist: pydantic>=2.11.7
Requires-Dist: python-dateutil>=2.8.0
Requires-Dist: ruff==0.13.0
Requires-Dist: typing-extensions>=4.0.0
Requires-Dist: urllib3>=2.5.0
Provides-Extra: dev
Requires-Dist: coverage[toml]>=7.0.0; extra == 'dev'
Requires-Dist: mypy>=1.0.0; extra == 'dev'
Requires-Dist: pre-commit>=3.0.0; extra == 'dev'
Requires-Dist: pytest-asyncio>=0.21.0; extra == 'dev'
Requires-Dist: pytest-cov>=4.0.0; extra == 'dev'
Requires-Dist: pytest-mock>=3.10.0; extra == 'dev'
Requires-Dist: pytest>=7.0.0; extra == 'dev'
Requires-Dist: ruff>=0.1.0; extra == 'dev'
Provides-Extra: test
Requires-Dist: coverage>=7.0.0; extra == 'test'
Requires-Dist: pytest-asyncio>=0.21.0; extra == 'test'
Requires-Dist: pytest-mock>=3.10.0; extra == 'test'
Requires-Dist: pytest>=7.0.0; extra == 'test'
